odoo10_addon_product_state-10.0.1.0.0-py2.7-nspkg.pth
odoo/addons/product_state/README.rst
odoo/addons/product_state/__init__.py
odoo/addons/product_state/__manifest__.py
odoo/addons/product_state/models/__init__.py
odoo/addons/product_state/models/product_template.py
odoo/addons/product_state/views/product_views.xml
odoo10_addon_product_state-10.0.1.0.0.dist-info/DESCRIPTION.rst
odoo10_addon_product_state-10.0.1.0.0.dist-info/METADATA
odoo10_addon_product_state-10.0.1.0.0.dist-info/RECORD
odoo10_addon_product_state-10.0.1.0.0.dist-info/WHEEL
odoo10_addon_product_state-10.0.1.0.0.dist-info/metadata.json
odoo10_addon_product_state-10.0.1.0.0.dist-info/namespace_packages.txt
odoo10_addon_product_state-10.0.1.0.0.dist-info/top_level.txt
